doc2code_assistant/__init__.py
doc2code_assistant/app.py
doc2code_assistant-0.1.0.dist-info/licenses/LICENSE
doc2code_assistant-0.1.0.dist-info/METADATA
doc2code_assistant-0.1.0.dist-info/WHEEL
doc2code_assistant-0.1.0.dist-info/entry_points.txt
doc2code_assistant-0.1.0.dist-info/top_level.txt
doc2code_assistant-0.1.0.dist-info/RECORD
