Metadata-Version: 2.4
Name: doc2code_assistant
Version: 0.1.0
Summary: Your own AI coding assistant based on your documentation using open models (like Ollama) + Streamlit
Author-email: Diego Villegas <diegoavillegasg@gmail.com>
License: MIT
Requires-Python: >=3.10
License-File: LICENSE
Requires-Dist: streamlit
Requires-Dist: llama-index
Requires-Dist: llama-index-llms-ollama
Requires-Dist: llama-index-embeddings-huggingface
Dynamic: license-file
